mcp_generate_number/__init__.py
mcp_generate_number/server.py
mcp_generate_number-0.1.22.dist-info/METADATA
mcp_generate_number-0.1.22.dist-info/WHEEL
mcp_generate_number-0.1.22.dist-info/entry_points.txt
mcp_generate_number-0.1.22.dist-info/top_level.txt
mcp_generate_number-0.1.22.dist-info/RECORD
