Metadata-Version: 2.4
Name: mcp-generate-number
Version: 0.1.22
Summary: An MCP server to generate random numbers and strings.
Author-email: Toby Willcocks <toby@cursor.dev>
License-Expression: MIT
Classifier: Development Status :: 4 - Beta
Classifier: Programming Language :: Python
Requires-Python: >=3.8
Requires-Dist: fastmcp
